caluxPy_ext/CalculoPosicion.py
caluxPy_ext/ExtraccionBGD.py
caluxPy_ext/__initi__.py
caluxpy_ext-0.1.2.dist-info/METADATA
caluxpy_ext-0.1.2.dist-info/WHEEL
caluxpy_ext-0.1.2.dist-info/licenses/LICENSE
caluxpy_ext-0.1.2.dist-info/RECORD
