Metadata-Version: 2.1
Name: caluxPy_ext
Version: 0.1.2
Summary: Data Extraction Tool
Author-email: Luis Manuel Tavarez Valenzuela <luima2494@gmail.com>
License-File: LICENSE
Classifier: License :: OSI Approved :: MIT License
Classifier: Operating System :: OS Independent
Classifier: Programming Language :: Python :: 3
Requires-Python: >=3.12
